[{"__type__":"cc.SpriteFrame","content":{"name":"baishuzi_0","texture":"18uE96PKtJm6bB8/SmH08P","rect":[0,0,252,99],"offset":[-2,78.5],"originalSize":[256,256]}},{"__type__":"cc.BitmapFont","_name":"baishuzi","spriteFrame":{"__uuid__":"56behABCJNnoqw2pplnX9y"},"fontSize":32,"_fntConfig":{"commonHeight":32,"fontSize":32,"atlasName":"baishuzi_0.png","fontDefDictionary":{"48":{"rect":{"x":0,"y":0,"width":36,"height":50},"xOffset":0,"yOffset":0,"xAdvance":36},"49":{"rect":{"x":72,"y":51,"width":20,"height":48},"xOffset":0,"yOffset":0,"xAdvance":20},"50":{"rect":{"x":218,"y":0,"width":34,"height":49},"xOffset":0,"yOffset":0,"xAdvance":34},"51":{"rect":{"x":74,"y":0,"width":35,"height":50},"xOffset":0,"yOffset":0,"xAdvance":35},"52":{"rect":{"x":0,"y":51,"width":38,"height":48},"xOffset":0,"yOffset":0,"xAdvance":38},"53":{"rect":{"x":182,"y":0,"width":35,"height":49},"xOffset":0,"yOffset":0,"xAdvance":35},"54":{"rect":{"x":110,"y":0,"width":35,"height":50},"xOffset":0,"yOffset":0,"xAdvance":35},"55":{"rect":{"x":39,"y":51,"width":32,"height":48},"xOffset":0,"yOffset":0,"xAdvance":32},"56":{"rect":{"x":37,"y":0,"width":36,"height":50},"xOffset":0,"yOffset":0,"xAdvance":36},"57":{"rect":{"x":146,"y":0,"width":35,"height":50},"xOffset":0,"yOffset":0,"xAdvance":35}},"kerningDict":{}}}]